{
	"activity": "سرگرمی",
	"add_file": "فائلیں شامل کریں",
	"add_sample_data": "نمونہ ڈیٹا شامل کریں",
	"ai_assistant": "AI معاون",
	"alert_limit_of_emails": "توجہ، ای میل کی حد ختم ہو گئی ہے۔",
	"all": "تمام",
	"all_records_found": "تمام ریکارڈ مل گئے",
	"altitude": "بلندی",
	"analyze_database": "ڈیٹا بیس کا تجزیہ کریں",
	"analyze_database_info": "بہترین کارکردگی کے لیے ڈیٹا بیس پر \"ANALYZE\" کمانڈ چلائیں۔",
	"and": "اور",
	"apply": "لاگو کریں",
	"are_you_sure_to_delete_note": "کیا آپ واقعی یہ نوٹ حذف کرنا چاہتے ہیں؟",
	"are_you_sure_to_delete_reference": "کیا آپ واقعی یہ حوالہ حذف کرنا چاہتے ہیں؟",
	"are_you_sure_to_delete_this_record": "کیا آپ واقعی یہ ریکارڈ حذف کرنا چاہتے ہیں؟",
	"ascending": "صعودی",
	"audiovisual": "سمعی بصری",
	"back_to_login": "لاگ ان پر واپس جائیں",
	"backfill_search_stores": "تلاش کے ذخائر بھریں",
	"backfill_search_stores_info": "ریکارڈ ڈیٹا سے اخذ کردہ تلاش کے ذخائر (matrix_string_search، matrix_relation_index) دوبارہ بناتا ہے۔ \"ڈیٹا بیس کے اثاثے دوبارہ بنائیں\" کے بعد استعمال کریں۔ بڑے ڈیٹا بیس پر چند منٹ لگتے ہیں۔",
	"beginning": "شروع",
	"begins_with": "سے شروع ہوتا ہے",
	"between": "کے درمیان",
	"build": "بنائیں",
	"build_database_version": "ڈیٹا بیس ورژن بنائیں",
	"by_user": "صارف کے ذریعہ",
	"caches_and_sessions": "کیش اور سیشن",
	"cancel": "منسوخ کریں",
	"cancel_upload": "اپ لوڈ منسوخ کریں",
	"change_order_for": "کے لیے ترتیب تبدیل کریں ",
	"change_user": "تبدیل کریں",
	"changes": "تبدیلیاں",
	"check": "جانچیں",
	"check_config": "کنفیگ جانچیں",
	"children_recursive": "ذیلی",
	"choose_page_between": "${page_in} اور ${page_out} کے درمیان صفحہ منتخب کریں۔ کل صفحات: ${total_pages}۔",
	"clean": "صاف کریں",
	"clear_cache_files": "کیش صاف کریں",
	"clear_session_files": "میعاد ختم سیشن صاف کریں",
	"code": "کوڈ",
	"collapse": "سمیٹیں / پھیلائیں",
	"component": "جزو",
	"component_alternative": "متبادل فیلڈ۔ جب تک اصطلاح معیاری نہ ہو استعمال نہ کریں۔ اس کے بجائے استعمال کریں: %s",
	"component_deprecated": "ختم ہونے والا فیلڈ۔ یہ فیلڈ اس میں ضم ہو رہا ہے: %s",
	"component_history": "جزو کی تاریخ",
	"component_tipo": "جزو tipo",
	"config_has_errors": "کنفیگریشن ٹیسٹ میں نقائص ہیں!",
	"config_has_passed": "کنفیگریشن ٹیسٹ پاس!",
	"conform_headers": "ہیڈر کو ہم شکل بنائیں",
	"consolidate_table_sequences": "جدول کی ترتیب کو یکجا کریں",
	"consolidate_table_sequences_info": "id ترتیب کو 1,2,... سے یکجا کرنے کے لیے جدول کے id کالم کو دوبارہ نمبر دیتا ہے۔ <br>[dd_ontology, matrix_ontology, matrix_ontology_main, matrix_dd]",
	"contains": "شامل ہے",
	"continue": "جاری رکھیں",
	"continue_label": "جاری رکھیں",
	"copy": "نقل کریں",
	"create": "بنائیں",
	"create_directories": "غائب ڈائریکٹریاں بنائیں",
	"create_fragment": "ٹکڑا بنائیں",
	"created": "بنایا گیا",
	"current_record": "موجودہ ریکارڈ",
	"data": "ڈیٹا",
	"data_was_not_modified_save_canceled": "ڈیٹا میں تبدیلی نہیں کی گئی۔ محفوظ کرنا منسوخ۔",
	"date": "تاریخ",
	"day": "دن",
	"days": "دن",
	"db_config_check_invalid": "ڈیٹا بیس: db کنفیگ غلط!",
	"db_config_check_ok": "ڈیٹا بیس: db کنفیگ ٹھیک ہے",
	"db_connection_check_invalid": "ڈیٹا بیس: db کنکشن غلط!",
	"db_connection_check_ok": "ڈیٹا بیس: db کنکشن ٹھیک ہے",
	"db_info_key_invalid": "ڈیٹا بیس: معلومات کلیدی کنفیگ غلط!",
	"db_info_key_ok": "ڈیٹا بیس: معلومات کلیدی کنفیگ ٹھیک ہے",
	"db_information_invalid": "ڈیٹا بیس: معلومات کنفیگ غلط!",
	"db_information_ok": "ڈیٹا بیس: معلومات کنفیگ ٹھیک ہے",
	"db_name_invalid": "ڈیٹا بیس: db نام کنفیگ غلط!",
	"db_name_ok": "ڈیٹا بیس: db نام کنفیگ ٹھیک ہے",
	"db_pw_invalid": "ڈیٹا بیس: پاس ورڈ کنفیگ غلط!",
	"db_pw_ok": "ڈیٹا بیس: پاس ورڈ کنفیگ ٹھیک ہے",
	"db_username_invalid": "ڈیٹا بیس: صارف نام کنفیگ غلط!",
	"db_username_ok": "ڈیٹا بیس: صارف نام کنفیگ ٹھیک ہے",
	"db_writable_check_invalid": "ڈیٹا بیس: db قابل تحریر نہیں! صارف کی اجازتیں چیک کریں",
	"db_writable_check_ok": "ڈیٹا بیس: db قابل تحریر ٹھیک ہے",
	"debug": "ڈیبگ",
	"default_data_language": "پہلے سے طے شدہ ڈیٹا زبان",
	"default_interface_language": "پہلے سے طے شدہ انٹرفیس زبان",
	"definition": "تعریف",
	"delete": "حذف کریں",
	"delete_data_and_record": "ڈیٹا اور ریکارڈ حذف کریں",
	"delete_data_only": "صرف ڈیٹا حذف کریں",
	"delete_diffusion_records": "پھیلاؤ کے ریکارڈ حذف کریں",
	"delete_file": "فائل حذف کریں",
	"delete_found_records": "تمام ملے ہوئے ریکارڈ حذف کر دیے جائیں گے۔",
	"delete_only_the_link": "صرف لنک حذف کریں",
	"delete_resource_and_links": "وسیلہ اور تمام لنک حذف کریں",
	"deleted_tags": "حذف شدہ ٹیگ",
	"descending": "نزولی",
	"developer": "ڈویلپر",
	"diameter": "قطر",
	"different_from": "سے مختلف",
	"diffusion": "پھیلاؤ",
	"digitization": "ڈیجیٹائزیشن",
	"discard_changes": "غیر محفوظ تبدیلیاں ترک کریں؟",
	"does_not_contain": "شامل نہیں ہے",
	"download": "ڈاؤن لوڈ",
	"duplicate": "نقل",
	"duplicated": "نقل شدہ",
	"edit": "ترمیم",
	"email": "ای میل",
	"email_limit_explanation": "بھیجنے کے لیے منتخب کردہ ای میلز آپ کے آپریٹنگ سسٹم کی زیادہ سے زیادہ حد سے تجاوز کر گئی ہیں، لہذا ہم نے پیکیج بنائے ہیں جو اس حد سے تجاوز نہیں کرتے۔ ای میلز بنانے کے لیے درج ذیل بٹن پر کلک کریں۔",
	"empty": "خالی",
	"empty_selection": "خالی انتخاب",
	"enable_mailer": "باہر جانے والی ای میل فعال کریں (پاس ورڈ کی بازیابی)",
	"encryption": "خفیہ کاری",
	"end_with": "پر ختم ہوتا ہے",
	"enter_recovery_code": "8 ہندسوں کا بازیابی کوڈ درج کریں",
	"enter_username_or_email": "براہ کرم اپنا صارف نام یا ای میل درج کریں",
	"entity_invalid": "ہستی کا نام ایک حرف سے شروع ہونا چاہیے اور صرف حروف، اعداد اور زیرِ خط پر مشتمل ہو (کوئی خلا نہیں)۔ کوشش کریں: ",
	"entity_label": "ہستی کا لیبل",
	"environment": "ماحول",
	"error": "نقص",
	"error_invalid_date_format": "نقص: تاریخ کی شکل غلط ہے",
	"error_on_upload_file": "فائل اپ لوڈ کرنے میں نقص",
	"errors_found": "نقائص پائے گئے",
	"exactly": "بالکل",
	"exceeded_limit": "اس فیلڈ کے لیے قدروں کی زیادہ سے زیادہ تعداد ختم ہو گئی ہے۔ حد =",
	"export_hierarchy": "درجہ بندی برآمد کریں",
	"export_presets": "پری سیٹ برآمد کریں",
	"extension": "ایکسٹینشن",
	"fail_to_save": "محفوظ کرنے میں ناکام!",
	"failed_install_context": "سرور ڈیٹا بیس کی حالت کے لیے سیاق حاصل کرنے میں ناکام رہا",
	"fields": "فیلڈز",
	"file": "فائل",
	"file_path": "فائل کا راستہ",
	"filesize_is_too_big": "فائل کا سائز بہت بڑا ہے",
	"filter": "فلٹر",
	"find": "تلاش کریں",
	"find_and_replace": "تلاش کریں اور بدلیں",
	"form": "فارم",
	"format": "فارمیٹ",
	"found_records": "تمام ملے ہوئے ریکارڈ",
	"fragment": "ٹکڑا",
	"from_address": "بھیجنے والے کا پتہ",
	"from_name": "بھیجنے والے کا نام (اختیاری)",
	"full_screen": "مکمل اسکرین",
	"generated_secrets_warning": "⚠ ان رازوں کو ابھی محفوظ کریں — یہ صرف ایک بار دکھائے جاتے ہیں اور بعد میں کبھی تبدیل نہیں ہونے چاہئیں:",
	"go_to_page": "صفحہ پر جائیں",
	"go_to_record": "ریکارڈ پر جائیں",
	"graph": "گراف",
	"graph_hint": "کسی نوڈ پر کلک کریں تاکہ اس کے روابط پھیلائیں یا سمیٹیں۔ Ctrl/Cmd + کلک ریکارڈ کھولتا ہے۔",
	"greater_than": "سے بڑا",
	"greater_than_or_equal": "سے بڑا یا برابر",
	"head": "ہیڈر",
	"hierarchies": "درجہ بندیاں",
	"hostname": "میزبان",
	"hour": "گھنٹہ",
	"import": "درآمد کریں",
	"import_hierarchies": "درجہ بندیاں درآمد کریں",
	"import_hierarchies_button": " درجہ بندیاں درآمد کریں ",
	"import_hierarchies_description": "یہ تھیسورس میں دکھایا جائے گا۔ ذہن میں رکھیں کہ بڑے ممالک بہت زیادہ وسائل استعمال کر سکتے ہیں۔ غیر ضروری ممالک لوڈ نہ کریں۔ آپ بعد میں مزید ممالک لوڈ کر سکتے ہیں۔",
	"import_hierarchies_directory_description": "ماخذ فائلوں کی ڈائریکٹری: ",
	"import_hierarchies_label": "درجہ بندیاں انسٹال کریں",
	"incremental": "اضافاتی",
	"index_name": "اشاریہ نام",
	"indexations": "اشارہ سازی",
	"indexations_info": "اشاریہ معلومات",
	"indexes": "اشاریہ جات",
	"info_key": "انسٹال معلومات کلید",
	"information": "معلومات",
	"insert_tag": "ٹیگ داخل کریں",
	"inspector": "معائنہ کار",
	"install": "انسٹال کریں",
	"install_db_label": "Dédalo ڈیٹا بیس انسٹال کریں",
	"install_done": "مکمل!",
	"install_information": "انسٹال معلومات",
	"installation_config": "انسٹالیشن کنفیگ: ",
	"installation_config_test": "کنفیگریشن",
	"installation_db": "انسٹال ڈیٹا بیس ماخذ فائل: ",
	"installation_db_config": "ڈیٹا بیس (PostgreSQL)",
	"installation_db_error_file_path": "ڈیٹا بیس فائل نہیں ملی! براہ کرم یقینی بنائیں کہ انسٹالیشن فائل یہاں موجود ہے: ",
	"installation_db_prereq": "پیشگی شرط: ایک قابل رسائی PostgreSQL ڈیٹا بیس جس کا کردار ٹیبلز، اشاریہ جات اور فنکشنز بنا سکے۔ کنکشن کی تفصیلات درج کریں اور انہیں جانچیں۔",
	"installation_diffusion": "پھیلاؤ ڈیٹا بیس (اختیاری)",
	"installation_diffusion_help": "اختیاری: پھیلاؤ انجن MariaDB/MySQL ڈیٹا بیس استعمال کرتا ہے۔ اسے صرف اس صورت میں فعال کریں جب آپ مواد شائع کریں گے۔ آپ بعد میں کنفیگر کر سکتے ہیں۔",
	"installation_directories": "ڈائریکٹریاں اور اجازتیں",
	"installation_directories_help": "Dédalo کو اپنی ورکنگ ڈائریکٹریز (private, sessions, cache, media, backup) پر لکھنے کی اجازت درکار ہے۔ انہیں چیک کریں اور جو غائب ہیں انہیں بنائیں۔",
	"installation_entity": "ہستی اور انسٹال معلومات",
	"installation_entity_help": "اس انسٹالیشن کی شناخت کریں۔ معلومات اور معلومات کلید ایک بار سیٹ کی جاتی ہیں اور بعد میں تبدیل نہیں ہونی چاہئیں (یہ محفوظ کردہ اسناد کی خفیہ کاری کا حصہ ہیں)۔",
	"installation_from_file": "فائل سے ڈیٹا بیس انسٹال کریں",
	"installation_help_info": "انسٹالیشن معلومات: ",
	"installation_mailer": "باہر جانے والی ای میل (اختیاری)",
	"installation_mailer_help": "اختیاری: باہر جانے والی ای میل صارفین کو لاگ ان اسکرین سے بھولا ہوا پاس ورڈ بازیاب کرنے دیتی ہے (انہیں 8 ہندسوں کا کوڈ ای میل کیا جاتا ہے)۔ Dédalo موجودہ SMTP میل باکس کے ذریعے ریلے کرتا ہے — یہ کبھی اپنا میل سرور نہیں چلاتا۔ آپ اسے بعد میں ../private/.env میں کنفیگر کر سکتے ہیں۔",
	"installation_persist": "کنفیگریشن محفوظ کریں",
	"installation_persist_help": "کنفیگریشن کو ../private/.env میں محفوظ کریں (ویب روٹ سے باہر، chmod 600)۔ مضبوط راز بنائے جائیں گے اور ایک بار دکھائے جائیں گے — انہیں محفوظ رکھیں۔",
	"installed": "انسٹال شدہ",
	"interface": "انٹرفیس",
	"invalid_auth_code": "غلط تصدیقی کوڈ!",
	"invalid_component": "غلط جزو",
	"invalid_extension": "غلط ایکسٹینشن",
	"invalid_username": "غلط صارف نام",
	"label_to_review": "جائزہ لیں",
	"language": "زبان",
	"language_default_invalid": "پہلے سے طے شدہ انٹرفیس اور ڈیٹا زبانیں منتخب کردہ زبانوں میں شامل ہونی چاہئیں",
	"languages_required": "کم از کم ایک کام کرنے والی زبان منتخب کریں",
	"latest_changes": "تازہ ترین تبدیلیاں",
	"latitude": "عرض البلد",
	"layer": "پرت",
	"layer_selector": "پرت منتخب کنندہ",
	"less_than": "سے کم",
	"less_than_or_equal": "سے کم یا برابر",
	"levels": "سطحیں",
	"lines": "سطور",
	"link_resource": "وسیلہ منسلک کریں",
	"list": "فہرست",
	"list_from_component_data": "جزو ڈیٹا سے فہرست",
	"load": "رپورٹس لوڈ کریں",
	"load_more": "مزید لوڈ کریں",
	"loading": "لوڈ ہو رہا ہے...",
	"loading_dedalo_files": "Dédalo فائلیں لوڈ ہو رہی ہیں",
	"locale": "مقام",
	"logged": "لاگ ان کیا",
	"login_label": "لاگ ان",
	"longitude": "طول البلد",
	"maintenance_cat_config": "کنفیگریشن اور کوڈ",
	"maintenance_cat_data": "بیک اپ اور ڈیٹا",
	"maintenance_cat_dev": "ڈویلپر اور جانچ",
	"maintenance_cat_diffusion": "پھیلاؤ",
	"maintenance_cat_integrity": "سلامتی اور نگرانی",
	"maintenance_cat_migration": "منتقلی اور تبدیلی",
	"maintenance_cat_publication": "اشاعت",
	"maintenance_cat_system": "نظام اور ماحول",
	"maintenance_find_tool": "ٹول تلاش کریں",
	"maintenance_map_hint": "کسی ذیلی نظام پر کلک کریں تاکہ اس کی حالت اور اس پر عمل کرنے والے ٹولز دیکھ سکیں۔",
	"maintenance_view_list": "فہرست",
	"maintenance_view_map": "نقشہ",
	"make_backup": "بیک اپ بنائیں",
	"mapa": "نقشہ",
	"match_case": "حالات کا مطابقت",
	"max": "زیادہ سے زیادہ",
	"media_control": "میڈیا کنٹرول",
	"min": "کم سے کم",
	"minute": "منٹ",
	"model": "ماڈل",
	"modified": "ترمیم شدہ",
	"modo": "موڈ",
	"month": "مہینہ",
	"months": "مہینے",
	"more": "مزید",
	"move_lang": "زبان منتقل کریں",
	"move_locator": "لوکیٹر منتقل کریں",
	"move_tld": "TLD منتقل کریں",
	"move_to_portal": "پورٹل پر منتقل کریں",
	"move_to_table": "جدول میں منتقل کریں",
	"name": "نام",
	"never": "کبھی نہیں",
	"new": "نیا",
	"new_password": "نیا پاس ورڈ",
	"new_pw_retype": "پاس ورڈ دوبارہ ٹائپ کریں",
	"new_tag": "نیا ٹیگ",
	"next": "اگلا",
	"no": "نہیں",
	"no_access": "یہاں رسائی نہیں ہے",
	"no_empty": "اس میں معلومات ہے",
	"no_records": "کوئی ریکارڈ نہیں ملا",
	"no_results": "کوئی درجہ بندی فلٹر سے مطابقت نہیں رکھتی۔",
	"no_tag_selected": "کوئی ٹیگ منتخب نہیں۔ اگر آپ جاری رکھیں گے تو پورا ریکارڈ اشاریہ جات میں آ جائے گا۔",
	"no_tools_match": "آپ کی تلاش سے کوئی ٹول مطابقت نہیں رکھتا",
	"not_allow_to_create_note": "کسی ایسی تبدیلی کے نوٹ نہیں بنا سکتے جو آپ کی نہیں ہے",
	"note": "نوٹ",
	"now": "ابھی",
	"of": "کا",
	"ok": "ٹھیک ہے",
	"ontology": "آنٹولوجی",
	"open": "کھولیں",
	"open_relationships": "روابط کھولیں",
	"open_relationships_of_field": "موجودہ ریکارڈ (1) سے یا تمام ملے ہوئے ریکارڈز ({1}) سے {0} کے روابط کھولیں؟",
	"open_site_builder": "سائٹ بلڈر کھولیں",
	"operator": "عامل",
	"optimize_tables": "جدول کو بہتر بنائیں",
	"optimize_tables_info": "منتخب جدولوں کو دوبارہ اشاریہ بند کرتا ہے اور vacuum analyze چلاتا ہے۔",
	"options": "اختیارات",
	"or": "یا",
	"original": "اصلی",
	"others": "دیگر",
	"page": "صفحہ",
	"password": "پاس ورڈ",
	"password_too_short": "پاس ورڈ بہت چھوٹا ہے۔ کم از کم 8 حروف استعمال کریں",
	"password_updated": "آپ کا پاس ورڈ اپ ڈیٹ ہو گیا ہے۔ اب آپ لاگ ان کر سکتے ہیں۔",
	"passwords_do_not_match": "پاس ورڈ مماثل نہیں ہیں",
	"persons": "افراد",
	"play": "چلائیں",
	"port": "پورٹ",
	"preset": "پری سیٹ",
	"previous": "پچھلا",
	"print": "پرنٹ کریں",
	"processing": "عملدرآمد",
	"project": "منصوبہ",
	"provisional": "عارضی",
	"publish": "شائع کریں",
	"published": "شائع شدہ",
	"rebuild_constraints": "رکاوٹیں دوبارہ بنائیں",
	"rebuild_constraints_info": "PostgreSQL کی اہم رکاوٹوں کو دوبارہ بنانے پر مجبور کرتا ہے۔",
	"rebuild_functions": "فنکشنز دوبارہ بنائیں",
	"rebuild_functions_info": "PostgreSQL کے اہم فنکشنز کو دوبارہ بنانے پر مجبور کرتا ہے۔",
	"rebuild_indexes": "اشاریہ جات دوبارہ بنائیں",
	"rebuild_indexes_info": "PostgreSQL کے اہم اشاریہ جات کو دوبارہ بنانے پر مجبور کرتا ہے۔",
	"rebuild_user_stats": "صارف کے اعدادوشمار دوبارہ بنائیں",
	"rebuild_user_stats_info": "صارف کی سرگرمی کے اعدادوشمار دوبارہ بناتا ہے، جو matrix_activity جدول سے شمار کیے جاتے ہیں اور dd1521 سیکشن میں روزانہ کے خلاصوں کے طور پر محفوظ کیے جاتے ہیں۔",
	"record": "ریکارڈ",
	"records_displayed": "Z میں سے X سے Y تک دکھائے گئے ریکارڈ",
	"recover_password": "پاس ورڈ بھول گئے؟",
	"recover_password_help": "اپنا صارف نام یا ای میل پتہ درج کریں اور ہم آپ کو 8 ہندسوں کا بازیابی کوڈ بھیجیں گے۔",
	"recover_password_title": "اپنا پاس ورڈ بازیاب کریں",
	"recovery_code_help": "ہم نے آپ کے ای میل پر 8 ہندسوں کا کوڈ بھیجا ہے۔ اسے اپنے نئے پاس ورڈ کے ساتھ نیچے درج کریں۔",
	"recovery_code_sent": "اگر اکاؤنٹ مماثل ہے تو، بازیابی کوڈ بھیج دیا گیا ہے۔",
	"recovery_code_title": "اپنا ای میل چیک کریں",
	"recovery_invalid_or_expired": "غلط یا میعاد ختم کوڈ",
	"recovery_reset_failed": "پاس ورڈ اپ ڈیٹ نہیں کیا جا سکا۔ براہ کرم بعد میں دوبارہ کوشش کریں۔",
	"recovery_too_many_attempts": "بہت زیادہ کوششیں۔ براہ کرم نیا کوڈ کی درخواست کریں۔",
	"recreate_db_assets": "ڈیٹا بیس کے اثاثے دوبارہ بنائیں",
	"recreate_db_assets_info": "تمام PostgreSQL اہم اشاریہ جات، رکاوٹوں، ایکسٹینشنز اور فنکشنز کو دوبارہ بنانے پر مجبور کرتا ہے۔",
	"references": "حوالہ جات",
	"refresh": "ریفریش",
	"register_tools": "ٹولز رجسٹر کریں",
	"register_tools_help": "دستیاب ٹولز (درآمد، برآمد، ٹائم مشین، …) رجسٹر کریں تاکہ وہ ایپلیکیشن میں ظاہر ہوں۔ یہ ٹولز ڈائریکٹری کو اسکین کرتا ہے اور ہر ٹول کو ڈیٹا بیس میں ریکارڈ کرتا ہے۔ آپ اسے بعد میں مینٹیننس → ٹولز رجسٹر کریں سے دوبارہ چلا سکتے ہیں۔",
	"relations": "روابط",
	"reload": "دوبارہ لوڈ کریں",
	"remaining": "باقی",
	"remove_filter": "فلٹر ہٹائیں",
	"repeat_password": "نیا پاس ورڈ دہرائیں",
	"replace": "بدلیں",
	"replace_all": "سب بدلیں",
	"request_code_first": "براہ کرم پہلے بازیابی کوڈ کی درخواست کریں",
	"required_fields": "براہ کرم ضروری فیلڈز بھریں",
	"reset": "ری سیٹ",
	"reset_password": "پاس ورڈ ری سیٹ کریں",
	"reset_pick_installed": "ری سیٹ کرنے کے لیے ایک یا زیادہ پہلے سے انسٹال کردہ درجہ بندیاں منتخب کریں۔",
	"reset_to_seed": "سیڈ پر ری سیٹ کریں",
	"reset_warning": "یہ سیڈ سے حذف کرکے دوبارہ درآمد کرتا ہے، تمام مقامی ترامیم کو ختم کرتا ہے",
	"resize": "سائز تبدیل کریں",
	"reuse_tag": "ٹیگ دوبارہ استعمال کریں",
	"reverse_relations": "الٹے روابط",
	"rotate": "گھمائیں",
	"runtime_info": "انجن رن ٹائم",
	"save": "محفوظ کریں",
	"save_root_pw": " روٹ پاس ورڈ محفوظ کریں ",
	"saved": "محفوظ شدہ",
	"search": "تلاش",
	"search_in_all_langs": "تمام زبانوں میں تلاش کریں",
	"search_in_current_lang": "موجودہ زبان میں تلاش کریں",
	"search_operators": "تلاش کے عوامل",
	"search_presets": "صارف کی تلاش پری سیٹ",
	"searching": "تلاش ہو رہی ہے...",
	"second": "سیکنڈ",
	"section": "سیکشن",
	"section_tipo": "سیکشن tipo",
	"sections": "سیکشنز",
	"select_a_file": "آپ کو ایک فائل منتخب کرنی ہوگی",
	"select_one_project": "آپ کو کم از کم ایک منصوبہ منتخب کرنا ہوگا",
	"select_page_of_the_doc": "دستاویز کا ایک صفحہ منتخب کریں:",
	"select_search_section": "تلاش کا سیکشن منتخب کریں",
	"send_code": "بازیابی کوڈ بھیجیں",
	"sequence": "ترتیب",
	"set_img_layer": "تصویر کی پرت سیٹ کریں",
	"set_root_pw_label": "روٹ پاس ورڈ سیٹ کریں",
	"show_all": "سب دکھائیں",
	"show_buttons": "بٹن دکھائیں",
	"show_last_files": "آخری فائلیں دکھائیں",
	"show_pw": "دکھائیں",
	"similar_to": "مشابہ",
	"site_in_recovery_mode": "انتباہ: نظام بازیابی موڈ میں ہے، آپ کی اہم آنٹولوجی شاید خراب ہے!",
	"site_under_maintenance": "نظام دیکھ بھال کے تحت ہے۔ تکلیف کے لیے معذرت",
	"situation": "ریکارڈ کی حالت",
	"size": "سائز",
	"skip": "پھیلاؤ چھوڑیں",
	"skip_mailer": "باہر جانے والی ای میل چھوڑیں",
	"smtp_from_help": "باہر جانے والی میل کا بھیجنے والے کا پتہ۔ خالی ہونے پر صارف نام استعمال ہوتا ہے۔",
	"smtp_secure_help": "tls = STARTTLS (پورٹ 587) · ssl = مضمر TLS (پورٹ 465) · none = غیر خفیہ کردہ (صرف لوکل ہوسٹ ریلے)",
	"socket": "Unix ساکٹ (اختیاری)",
	"sort": "ترتیب دیں",
	"source": "ماخذ",
	"standard": "معیاری",
	"start_upload": "اپ لوڈ شروع کریں",
	"state": "توثیق کی حالت",
	"sure": "کیا آپ کو یقین ہے؟",
	"sure_delete_entry_all_langs": "یہ اندراج تمام زبانوں سے حذف کر دیا جائے گا۔",
	"table": "جدول",
	"tag": "ٹیگ",
	"terms": "شرائط",
	"test_connection": "کنکشن جانچیں",
	"test_diffusion_first": "جاری رکھنے سے پہلے پھیلاؤ کنکشن کو کامیابی سے جانچیں (یا اسے غیر فعال کریں)۔",
	"test_mailer_first": "جاری رکھنے سے پہلے SMTP کنکشن کو کامیابی سے جانچیں (یا باہر جانے والی ای میل غیر فعال کریں)۔",
	"timecodes": "ٹائم کوڈز",
	"timezone": "ٹائم زون",
	"tipo": "tipo",
	"title": "عنوان",
	"to_change_pw": "روٹ تبدیل کرنے کے لیے",
	"to_install": "انسٹال کرنے کے لیے",
	"to_login": "لاگ ان کرنے کے لیے",
	"to_update": "اپ ڈیٹ کرنے کے لیے",
	"tool_import_files": "فائلیں درآمد کریں",
	"tool_import_marc21": "MARC 21 درآمد کریں",
	"tool_import_zotero": "Zotero سے درآمد کریں",
	"tool_indexation": "اشارہ سازی",
	"tool_lang": "زبان",
	"tool_qr": "QR کوڈز",
	"tool_structuration": "ساخت بندی",
	"tool_subtitles": "سب ٹائٹلز",
	"tool_transcription": "نقل",
	"tool_translation": "ترجمہ",
	"total": "کل",
	"total_records": "کل ریکارڈ",
	"translatable": "قابل ترجمہ",
	"translation": "ترجمہ",
	"type": "قسم",
	"type_root_password": "اپنا مطلوبہ سپر یوزر پاس ورڈ ٹائپ کریں اور دوبارہ ٹائپ کریں اور اسے محفوظ جگہ پر رکھیں۔ 8 سے 32 حروف کا ایک مضبوط پاس ورڈ استعمال کریں جس میں کم از کم ایک بڑا حرف، ایک چھوٹا حرف اور ایک عدد ہو۔ یکے بعد دیگرے ایک جیسے حروف کی اجازت نہیں ہے ('aa', '11', 'BB' وغیرہ)۔ عددی ('123', '345' وغیرہ) یا حروف تہجی ('aBC', 'hIjK' وغیرہ) ترتیب کی اجازت نہیں ہے۔",
	"unsaved_changes": "غیر محفوظ تبدیلیاں!",
	"update": "اپ ڈیٹ",
	"update_mode_mandatory": "اپ ڈیٹ موڈ لازمی ہے",
	"update_ontology": "آنٹولوجی اپ ڈیٹ کریں",
	"upload": "اپ لوڈ",
	"username": "صارف نام",
	"username_or_email": "صارف نام یا ای میل",
	"value": "قدر",
	"value_out_of_range": "قدر حد سے باہر ہے",
	"verify_active": "فعال کنفیگریشن کی تصدیق کریں",
	"version": "ورژن",
	"versions": "ورژن",
	"warning": "انتباہ",
	"weight": "وزن",
	"whole_words": "مکمل الفاظ",
	"will_open_all_related_records": "یہ تمام ریکارڈز کے {0} متعلقہ ڈیٹا کو فلٹر کیے بغیر ایک نئی ونڈو میں کھولے گا۔ کیا آپ کو یقین ہے؟",
	"working_languages": "کام کرنے والی زبانیں",
	"year": "سال",
	"years": "سال",
	"yes": "ہاں",
	"zoom": "زوم"
}
