{
	"activity": "Activity",
	"add_file": "Add files",
	"add_sample_data": "Add sample data",
	"ai_assistant": "AI Assistant",
	"alert_limit_of_emails": "Attention, exceeded the email limit.",
	"all": "All",
	"all_records_found": "All records found",
	"altitude": "Altitude",
	"analyze_database": "Analyze database",
	"analyze_database_info": "Exec \"ANALYZE\" command on database for optimal performance.",
	"and": "and",
	"apply": "Apply",
	"are_you_sure_to_delete_note": "Are you sure you want to delete this note?",
	"are_you_sure_to_delete_reference": "Are you sure you want to delete this reference?",
	"are_you_sure_to_delete_this_record": "Are you sure to delete this record?",
	"ascending": "ascending",
	"audiovisual": "Audiovisual",
	"back_to_login": "Back to login",
	"backfill_search_stores": "Backfill search stores",
	"backfill_search_stores_info": "Rebuilds the derived search stores (matrix_string_search, matrix_relation_index) from the record data. Use after \"Recreate database assets\". Takes minutes on large databases.",
	"beginning": "Beginning",
	"begins_with": "Begins with",
	"between": "Between",
	"build": "Build",
	"build_database_version": "Build database version",
	"by_user": "by user",
	"caches_and_sessions": "Caches & sessions",
	"cancel": "Cancel",
	"cancel_upload": "Cancel upload",
	"change_order_for": "Change order for ",
	"change_user": "Change",
	"changes": "changes",
	"check": "Check",
	"check_config": "Check config",
	"children_recursive": "Children",
	"choose_page_between": "Choose page between ${page_in} and ${page_out}. Total pages: ${total_pages}.",
	"clean": "Clean",
	"clear_cache_files": "Clear caches",
	"clear_session_files": "Clear expired sessions",
	"code": "Code",
	"collapse": "Collapse / expand",
	"component": "Component",
	"component_alternative": "Alternative field. Do not use unless the term is not normalized. Use instead: %s",
	"component_deprecated": "Field in the process of disappearing. This field merges with: %s",
	"component_history": "Component history",
	"component_tipo": "Component tipo",
	"config_has_errors": "Configuration test contains errors!",
	"config_has_passed": "Configuration test passed!",
	"conform_headers": "Conform headers",
	"consolidate_table_sequences": "Consolidate table sequences",
	"consolidate_table_sequences_info": "Renumbers table id column to consolidate id sequence from 1,2,... <br>[dd_ontology, matrix_ontology, matrix_ontology_main, matrix_dd]",
	"contains": "Contains",
	"continue": "Continue",
	"continue_label": "Continue",
	"copy": "Copy",
	"create": "Make",
	"create_directories": "Create missing directories",
	"create_fragment": "Create fragment",
	"created": "created",
	"current_record": "Current record",
	"data": "data",
	"data_was_not_modified_save_canceled": "The data was not modified. Save canceled.",
	"date": "Date",
	"day": "day",
	"days": "days",
	"db_config_check_invalid": "Database: db config invalid!",
	"db_config_check_ok": "Database: db config ok",
	"db_connection_check_invalid": "Database: db connection invalid!",
	"db_connection_check_ok": "Database: db connection ok",
	"db_info_key_invalid": "Database: information key config invalid!",
	"db_info_key_ok": "Database: information key config ok",
	"db_information_invalid": "Database: information config invalid!",
	"db_information_ok": "Database: information config ok",
	"db_name_invalid": "Database: db name config invalid!",
	"db_name_ok": "Database: db name config ok",
	"db_pw_invalid": "Database: pw config invalid!",
	"db_pw_ok": "Database: pw config ok",
	"db_username_invalid": "Database: username config invalid!",
	"db_username_ok": "Database: username config ok",
	"db_writable_check_invalid": "Database: db is not writable! Check user permissions",
	"db_writable_check_ok": "Database: db writable ok",
	"debug": "Debug",
	"default_data_language": "Default data language",
	"default_interface_language": "Default interface language",
	"definition": "Definition",
	"delete": "Delete",
	"delete_data_and_record": "Delete data and record",
	"delete_data_only": "Delete data only",
	"delete_diffusion_records": "Delete diffusion records",
	"delete_file": "Delete file",
	"delete_found_records": "All records found will be deleted.",
	"delete_only_the_link": "Delete only link",
	"delete_resource_and_links": "Delete resource and all links",
	"deleted_tags": "Deleted tags",
	"descending": "descending",
	"developer": "Developer",
	"diameter": "Diameter",
	"different_from": "Different from",
	"diffusion": "Diffusion",
	"digitization": "Digitization",
	"discard_changes": "Discard unsaved changes?",
	"does_not_contain": "Does not contain",
	"download": "Download",
	"duplicate": "Duplicate",
	"duplicated": "Duplicated",
	"edit": "Edit",
	"email": "E-mail",
	"email_limit_explanation": "The emails selected to send exceed the maximum limit of your operating system, so we have proceeded to create packages that do not exceed this maximum. Click on the following buttons to create the emails.",
	"empty": "Empty",
	"empty_selection": "Empty selection",
	"enable_mailer": "Enable outbound email (password recovery)",
	"encryption": "Encryption",
	"end_with": "Ends with",
	"enter_recovery_code": "Enter the 8-digit recovery code",
	"enter_username_or_email": "Please enter your username or email",
	"entity_invalid": "Entity name must start with a letter and contain only letters, numbers and underscores (no spaces). Try: ",
	"entity_label": "Entity label",
	"environment": "Environment",
	"error": "Error",
	"error_invalid_date_format": "Error: Date format is invalid",
	"error_on_upload_file": "Error on upload file",
	"errors_found": "Errors found",
	"exactly": "Exactly",
	"exceeded_limit": "The maximum number of values for this field has been exceeded. Limit =",
	"export_hierarchy": "Export hierarchy",
	"export_presets": "Export presets",
	"extension": "extension",
	"fail_to_save": "Fail to save!",
	"failed_install_context": "Server has failed to get context for db status",
	"fields": "Fields",
	"file": "File",
	"file_path": "File Path",
	"filesize_is_too_big": "File size is too big",
	"filter": "filter",
	"find": "Search",
	"find_and_replace": "Find and replace",
	"form": "Form",
	"format": "Format",
	"found_records": "All found records",
	"fragment": "fragment",
	"from_address": "From address",
	"from_name": "From name (optional)",
	"full_screen": "Full screen",
	"generated_secrets_warning": "⚠ Save these secrets now — they are shown only once and must never be changed later:",
	"go_to_page": "Go to page",
	"go_to_record": "Go to record",
	"graph": "Graph",
	"graph_hint": "Click a node to expand or collapse its relations. Ctrl/Cmd + click opens the record.",
	"greater_than": "Greater than",
	"greater_than_or_equal": "Greater than or equal",
	"head": "Header",
	"hierarchies": "hierarchies",
	"hostname": "Host",
	"hour": "hour",
	"import": "Import",
	"import_hierarchies": "Import hierarchies",
	"import_hierarchies_button": " Import hierarchies ",
	"import_hierarchies_description": "It will be displayed in the thesaurus. Keep in mind that large countries can consume a lot of resources. Don't load unnecessary countries. You can always load more countries later",
	"import_hierarchies_directory_description": "Source files directory: ",
	"import_hierarchies_label": "Install hierarchies",
	"incremental": "Incremental",
	"index_name": "Index Name",
	"indexations": "Indexations",
	"indexations_info": "Index info",
	"indexes": "Indexes",
	"info_key": "Install info key",
	"information": "Information",
	"insert_tag": "Insert tag",
	"inspector": "Inspector",
	"install": "Install",
	"install_db_label": "Install Dédalo DDBB",
	"install_done": "Done!",
	"install_information": "Install information",
	"installation_config": "Installation config: ",
	"installation_config_test": "Configuration",
	"installation_db": "Install DDBB source file: ",
	"installation_db_config": "Database (PostgreSQL)",
	"installation_db_error_file_path": "Database file not found! Please verify that the installation file exists in: ",
	"installation_db_prereq": "Prerequisite: an accessible PostgreSQL database whose role can create tables, indexes and functions. Enter the connection details and test them.",
	"installation_diffusion": "Diffusion database (optional)",
	"installation_diffusion_help": "Optional: the diffusion (publication) engine uses a MariaDB/MySQL database. Enable it only if you will publish content. You can configure it later.",
	"installation_directories": "Directories & permissions",
	"installation_directories_help": "Dédalo needs write permission on its working directories (private, sessions, cache, media, backup). Check them and create any that are missing.",
	"installation_entity": "Entity & install info",
	"installation_entity_help": "Identify this installation. The information and info key are set once and must not be changed afterwards (they are part of how stored credentials are encrypted).",
	"installation_from_file": "INSTALL DATABASE FROM FILE",
	"installation_help_info": "Installation info: ",
	"installation_mailer": "Outbound email (optional)",
	"installation_mailer_help": "Optional: outbound email lets users recover a forgotten password from the login screen (an 8-digit code is emailed to them). Dédalo relays through an existing SMTP mailbox — it never runs its own mail server. You can configure it later in ../private/.env.",
	"installation_persist": "Save configuration",
	"installation_persist_help": "Save the configuration to ../private/.env (outside the web root, chmod 600). Strong secrets will be generated and shown once — store them safely.",
	"installed": "Installed",
	"interface": "Interface",
	"invalid_auth_code": "Invalid auth code!",
	"invalid_component": "Invalid component",
	"invalid_extension": "Invalid extension",
	"invalid_username": "Invalid username",
	"label_to_review": "To review",
	"language": "Language",
	"language_default_invalid": "The default interface and data languages must be among the selected languages",
	"languages_required": "Select at least one working language",
	"latest_changes": "Latest changes",
	"latitude": "Latitude",
	"layer": "Layer",
	"layer_selector": "Layer selector",
	"less_than": "Less than",
	"less_than_or_equal": "Less than or equal to",
	"levels": "Levels",
	"lines": "Lines",
	"link_resource": "Link resource",
	"list": "List",
	"list_from_component_data": "List from component data",
	"load": "Load reports",
	"load_more": "Load more",
	"loading": "Loading...",
	"loading_dedalo_files": "Loading Dédalo files",
	"locale": "Locale",
	"logged": "Logged",
	"login_label": "Login",
	"longitude": "Longitude",
	"maintenance_cat_config": "Configuration & code",
	"maintenance_cat_data": "Backup & data",
	"maintenance_cat_dev": "Developer & testing",
	"maintenance_cat_diffusion": "Diffusion",
	"maintenance_cat_integrity": "Integrity & monitoring",
	"maintenance_cat_migration": "Migration & transform",
	"maintenance_cat_publication": "Publication",
	"maintenance_cat_system": "System & environment",
	"maintenance_find_tool": "Find a tool",
	"maintenance_map_hint": "Click a subsystem to see its status and the tools that act on it.",
	"maintenance_view_list": "List",
	"maintenance_view_map": "Map",
	"make_backup": "Make backup",
	"mapa": "Map",
	"match_case": "Match case",
	"max": "Max",
	"media_control": "Media control",
	"min": "Mín.",
	"minute": "minute",
	"model": "Model",
	"modified": "modified",
	"modo": "mode",
	"month": "month",
	"months": "months",
	"more": "more",
	"move_lang": "Move lang",
	"move_locator": "Move locator",
	"move_tld": "Move TLD",
	"move_to_portal": "Move to portal",
	"move_to_table": "Move to table",
	"name": "Name",
	"never": "Never",
	"new": "New",
	"new_password": "New password",
	"new_pw_retype": "Retype Password",
	"new_tag": "New tag",
	"next": "Next",
	"no": "no",
	"no_access": "No access here",
	"no_empty": "It contains information",
	"no_records": "No records found",
	"no_results": "No hierarchies match the filter.",
	"no_tag_selected": "No tag selected. If you continue, the entire record will be indexed.",
	"no_tools_match": "No tools match your search",
	"not_allow_to_create_note": "Cannot create notes of a change that is not yours",
	"note": "Note",
	"now": "Now",
	"of": "of",
	"ok": "OK",
	"ontology": "Ontology",
	"open": "Open",
	"open_relationships": "Open relationships",
	"open_relationships_of_field": "Open relationships of {0} from the current record (1) or from all found records ({1})?",
	"open_site_builder": "Open site builder",
	"operator": "Operator",
	"optimize_tables": "Optimize tables",
	"optimize_tables_info": "Re-index and vacuum analyze the selected tables.",
	"options": "Options",
	"or": "or",
	"original": "Original",
	"others": "Other",
	"page": "Page",
	"password": "Password",
	"password_too_short": "Password too short. Use at least 8 characters",
	"password_updated": "Your password has been updated. You can now log in.",
	"passwords_do_not_match": "Passwords do not match",
	"persons": "Persons",
	"play": "Play",
	"port": "Port",
	"preset": "Preset",
	"previous": "Previous",
	"print": "Print",
	"processing": "Processing",
	"project": "Project",
	"provisional": "Provisional",
	"publish": "Publish",
	"published": "Published",
	"rebuild_constraints": "Rebuild constraints",
	"rebuild_constraints_info": "Forces rebuilding PostgreSQL main constraints.",
	"rebuild_functions": "Rebuild functions",
	"rebuild_functions_info": "Forces rebuilding PostgreSQL main functions.",
	"rebuild_indexes": "Rebuild indexes",
	"rebuild_indexes_info": "Forces rebuild PostgreSQL main indexes.",
	"rebuild_user_stats": "Rebuild user stats",
	"rebuild_user_stats_info": "Re-create the user activity stats, calculated from table matrix_activity and saved in section dd1521 as daily summaries.",
	"record": "record",
	"records_displayed": "Displayed records from X to Y of Z",
	"recover_password": "Forgot your password?",
	"recover_password_help": "Enter your username or email address and we will send you an 8-digit recovery code.",
	"recover_password_title": "Recover your password",
	"recovery_code_help": "We sent an 8-digit code to your email. Enter it below with your new password.",
	"recovery_code_sent": "If an account matches, a recovery code has been sent.",
	"recovery_code_title": "Check your email",
	"recovery_invalid_or_expired": "Invalid or expired code",
	"recovery_reset_failed": "Could not update the password. Please try again later.",
	"recovery_too_many_attempts": "Too many attempts. Please request a new code.",
	"recreate_db_assets": "Recreate database assets",
	"recreate_db_assets_info": "Forces recreate all PostgreSQL main indexes, constraints, extensions and functions.",
	"references": "References",
	"refresh": "Refresh",
	"register_tools": "Register tools",
	"register_tools_help": "Register the available tools (import, export, time machine, …) so they appear in the application. This scans the tools directory and records each tool in the database. You can always re-run this later from Maintenance → Register tools.",
	"relations": "Relations",
	"reload": "Reload",
	"remaining": "remaining",
	"remove_filter": "Remove filter",
	"repeat_password": "Repeat new password",
	"replace": "Replace",
	"replace_all": "Replace all",
	"request_code_first": "Please request a recovery code first",
	"required_fields": "Please fill the required fields",
	"reset": "Reset",
	"reset_password": "Reset password",
	"reset_pick_installed": "Tick one or more already-installed hierarchies to reset.",
	"reset_to_seed": "Reset to seed",
	"reset_warning": "This DELETES and re-imports from the seed, discarding any local edits",
	"resize": "Resize",
	"reuse_tag": "Reuse tag",
	"reverse_relations": "Reverse relations",
	"rotate": "Rotate",
	"runtime_info": "Engine runtime",
	"save": "Save",
	"save_root_pw": " Save the root password ",
	"saved": "saved",
	"search": "Search",
	"search_in_all_langs": "Search in all langs",
	"search_in_current_lang": "Search in current lang",
	"search_operators": "Search operators",
	"search_presets": "User search preset",
	"searching": "Searching..",
	"second": "second",
	"section": "section",
	"section_tipo": "Section tipo",
	"sections": "sections",
	"select_a_file": "You must select a file",
	"select_one_project": "You must select at least one project",
	"select_page_of_the_doc": "Select a page of the document:",
	"select_search_section": "Select a search section",
	"send_code": "Send recovery code",
	"sequence": "Sequence",
	"set_img_layer": "Set image layer",
	"set_root_pw_label": "Set root password",
	"show_all": "Show all",
	"show_buttons": "Show buttons",
	"show_last_files": "Show last files",
	"show_pw": "Show",
	"similar_to": "Similar to",
	"site_in_recovery_mode": "WARNING: The system is in recovery mode, your main ontology is probably damaged!",
	"site_under_maintenance": "System under maintenance. Sorry for the inconvenience",
	"situation": "Registry state",
	"size": "Size",
	"skip": "Skip diffusion",
	"skip_mailer": "Skip outbound email",
	"smtp_from_help": "The sender address of outbound mail. When empty, the username is used.",
	"smtp_secure_help": "tls = STARTTLS (port 587) · ssl = implicit TLS (port 465) · none = unencrypted (localhost relays only)",
	"socket": "Unix socket (optional)",
	"sort": "Sort",
	"source": "Source",
	"standard": "Standard",
	"start_upload": "Start upload",
	"state": "Validation state",
	"sure": "Are you sure?",
	"sure_delete_entry_all_langs": "This entry will be deleted from all languages.",
	"table": "table",
	"tag": "tag",
	"terms": "Terms",
	"test_connection": "Test connection",
	"test_diffusion_first": "Test the diffusion connection successfully before continuing (or disable it).",
	"test_mailer_first": "Test the SMTP connection successfully before continuing (or disable outbound email).",
	"timecodes": "Time codes",
	"timezone": "Timezone",
	"tipo": "tipo",
	"title": "Title",
	"to_change_pw": "To change root",
	"to_install": "To install",
	"to_login": "To login",
	"to_update": "To update",
	"tool_import_files": "Import files",
	"tool_import_marc21": "Import MARC 21",
	"tool_import_zotero": "Import from Zotero",
	"tool_indexation": "Indexation",
	"tool_lang": "Language",
	"tool_qr": "QR codes",
	"tool_structuration": "Structuration",
	"tool_subtitles": "Subtitles",
	"tool_transcription": "Transcription",
	"tool_translation": "Translation",
	"total": "Total",
	"total_records": "Total records",
	"translatable": "Translatable",
	"translation": "Translation",
	"type": "Type",
	"type_root_password": "Type and retype your desired superuser password and keep it in a safe place. Use a strong password from 8 to 32 characters containing, at least, an upper-case letter, a lower-case letter, and a number. Identical characters in sequential order are not allowed ('aa', '11', 'BB', etc.). Numerical ('123', '345', etc.) nor alphabetical ('aBC', 'hIjK', etc.) order are allowed.",
	"unsaved_changes": "Unsaved changes!",
	"update": "Update",
	"update_mode_mandatory": "Update mode is mandatory",
	"update_ontology": "Update Ontology",
	"upload": "Upload",
	"username": "Username",
	"username_or_email": "Username or email",
	"value": "Value",
	"value_out_of_range": "Value out of range",
	"verify_active": "Verify active configuration",
	"version": "Version",
	"versions": "Versions",
	"warning": "Warning",
	"weight": "Weight",
	"whole_words": "Whole words",
	"will_open_all_related_records": "This will open all related data of {0} of all records in a new window without filtering. Are you sure?",
	"working_languages": "Working languages",
	"year": "year",
	"years": "years",
	"yes": "yes",
	"zoom": "Zoom"
}
